{
"type": "FeatureCollection",
"crs": { "type": "name", "properties": { "name": "urn:ogc:def:crs:OGC:1.3:CRS84" } },
"features": [
{ "type": "Feature", "properties": { "addr": "上海松江泗泾 中国铁建 花语天境" }, "geometry": { "type": "Point", "coordinates": [ 121.277755464184651, 31.124020950676233 ] } }
]
}
