{
"type": "FeatureCollection",
"crs": { "type": "name", "properties": { "name": "urn:ogc:def:crs:OGC:1.3:CRS84" } },
"features": [
{ "type": "Feature", "properties": { "addr": "松江 泗泾 中国铁建 花语天境 ", "price": "4.8W+", "visit": "1", "wiki": "https://junxnone.github.io/F/#/0025_%E4%B8%80%E6%89%8B%E6%88%BF_%E6%9D%BE%E6%B1%9F%E6%B3%97%E6%B3%BE_%E8%8A%B1%E8%AF%AD%E5%A4%A9%E9%95%9C" }, "geometry": { "type": "Point", "coordinates": [ 121.25488, 31.133354 ] } }
]
}
