{
"type": "FeatureCollection",
"crs": { "type": "name", "properties": { "name": "urn:ogc:def:crs:OGC:1.3:CRS84" } },
"features": [
{ "type": "Feature", "properties": { "addr": "奉贤 庄行 大名城 映雨江南 ", "price": "3W+", "visit": "1", "wiki": "https://junxnone.github.io/F/#/0022_%E4%B8%80%E6%89%8B%E6%88%BF_%E5%A5%89%E8%B4%A4%E5%BA%84%E8%A1%8C_%E5%A4%A7%E5%90%8D%E5%9F%8E%E6%98%A0%E9%9B%A8%E6%B1%9F%E5%8D%97" }, "geometry": { "type": "Point", "coordinates": [ 121.40403, 30.907324 ] } }
]
}
