{
"type": "FeatureCollection",
"crs": { "type": "name", "properties": { "name": "urn:ogc:def:crs:OGC:1.3:CRS84" } },
"features": [
{ "type": "Feature", "properties": { "addr": "上海奉贤庄行 大名城映雨江南" }, "geometry": { "type": "Point", "coordinates": [ 121.162668694451611, 31.295503147548555 ] } }
]
}
