{
"type": "FeatureCollection",
"crs": { "type": "name", "properties": { "name": "urn:ogc:def:crs:OGC:1.3:CRS84" } },
"features": [
{ "type": "Feature", "properties": { "addr": "上海市奉贤区 庄行 大名城映雨江南" }, "geometry": { "type": "Point", "coordinates": [ 121.464957481614292, 30.907328722637846 ] } }
]
}
