{
"type": "FeatureCollection",
"crs": { "type": "name", "properties": { "name": "urn:ogc:def:crs:OGC:1.3:CRS84" } },
"features": [
{ "type": "Feature", "properties": { "addr": "上海市奉贤区南亭公路与庄良公路交汇" }, "geometry": { "type": "Point", "coordinates": [ 121.404592878463134, 30.890861053233703 ] } }
]
}
